fastkml/__init__.py
fastkml/_registry_setup.py
fastkml/about.py
fastkml/abstract_geometry.py
fastkml/atom.py
fastkml/base.py
fastkml/config.py
fastkml/containers.py
fastkml/data.py
fastkml/enums.py
fastkml/exceptions.py
fastkml/features.py
fastkml/geometry.py
fastkml/helpers.py
fastkml/kml.py
fastkml/kml_base.py
fastkml/links.py
fastkml/mixins.py
fastkml/model.py
fastkml/network_link_control.py
fastkml/overlays.py
fastkml/py.typed
fastkml/registry.py
fastkml/styles.py
fastkml/times.py
fastkml/types.py
fastkml/utils.py
fastkml/validator.py
fastkml/views.py
fastkml/gx/__init__.py
fastkml/gx/data.py
fastkml/gx/track.py
fastkml/schema/atom-author-link.xsd
fastkml/schema/kml22gx.xsd
fastkml/schema/ogckml22.xsd
fastkml/schema/xAL.xsd
fastkml-1.3.0.dist-info/METADATA
fastkml-1.3.0.dist-info/WHEEL
fastkml-1.3.0.dist-info/top_level.txt
fastkml-1.3.0.dist-info/RECORD
