Metadata-Version: 2.4
Name: fastkml
Version: 1.3.0
Summary: Fast KML processing in python
Author-email: Christian Ledermann <christian.ledermann@gmail.com>
License: LGPL
Project-URL: Changelog, https://github.com/cleder/fastkml/blob/develop/docs/HISTORY.rst
Project-URL: Documentation, https://fastkml.readthedocs.org/
Project-URL: Homepage, https://github.com/cleder/fastkml
Classifier: Development Status :: 5 - Production/Stable
Classifier: Intended Audience :: Developers
Classifier: License :: OSI Approved :: GNU Library or Lesser General Public License (LGPL)
Classifier: Operating System :: OS Independent
Classifier: Programming Language :: Python
Classifier: Programming Language :: Python :: 3 :: Only
Classifier: Programming Language :: Python :: 3.9
Classifier: Programming Language :: Python :: 3.10
Classifier: Programming Language :: Python :: 3.11
Classifier: Programming Language :: Python :: 3.12
Classifier: Programming Language :: Python :: 3.13
Classifier: Programming Language :: Python :: 3.14
Classifier: Programming Language :: Python :: 3.15
Classifier: Programming Language :: Python :: Implementation :: CPython
Classifier: Programming Language :: Python :: Implementation :: GraalPy
Classifier: Programming Language :: Python :: Implementation :: PyPy
Classifier: Topic :: Scientific/Engineering :: GIS
Classifier: Topic :: Software Development :: Libraries
Classifier: Topic :: Software Development :: Libraries :: Python Modules
Classifier: Topic :: Text Processing :: Markup :: XML
Classifier: Typing :: Typed
Requires-Python: >=3.9
Requires-Dist: arrow
Requires-Dist: pygeoif>=1.5
Requires-Dist: typing-extensions>4
Provides-Extra: complexity
Requires-Dist: complexipy; extra == "complexity"
Requires-Dist: lizard; extra == "complexity"
Requires-Dist: radon; extra == "complexity"
Provides-Extra: dev
Requires-Dist: fastkml[complexity,docs,linting,lxml,tests,typing]; extra == "dev"
Requires-Dist: pre-commit; extra == "dev"
Requires-Dist: shapely; extra == "dev"
Provides-Extra: docs
Requires-Dist: Sphinx; extra == "docs"
Requires-Dist: pyshp; extra == "docs"
Requires-Dist: sphinx-autodoc-typehints; extra == "docs"
Requires-Dist: sphinx-rtd-theme; extra == "docs"
Provides-Extra: linting
Requires-Dist: flake8-cognitive-complexity; extra == "linting"
Requires-Dist: flake8-comments; extra == "linting"
Requires-Dist: flake8-encodings; extra == "linting"
Requires-Dist: flake8-expression-complexity; extra == "linting"
Requires-Dist: flake8-typing-imports; extra == "linting"
Requires-Dist: ruff; extra == "linting"
Requires-Dist: yamllint; extra == "linting"
Provides-Extra: lxml
Requires-Dist: lxml; extra == "lxml"
Provides-Extra: tests
Requires-Dist: hypothesis[dateutil]; extra == "tests"
Requires-Dist: pytest; extra == "tests"
Requires-Dist: pytest-cov; extra == "tests"
Requires-Dist: pytz; extra == "tests"
Requires-Dist: tzdata; extra == "tests"
Provides-Extra: typing
Requires-Dist: mypy; extra == "typing"
